transforms/__init__.py
transforms/safe_html.py
transforms/safe_html_utils.py
transforms/utils.py
transforms-0.2.1.dist-info/LICENSE
transforms-0.2.1.dist-info/METADATA
transforms-0.2.1.dist-info/WHEEL
transforms-0.2.1.dist-info/top_level.txt
transforms-0.2.1.dist-info/RECORD
