Metadata-Version: 2.1
Name: transforms
Version: 0.2.1
Summary: Python transforms
Author-email: Mikhail Kashkin <mkashkin@gmail.com>
License: MIT License
Project-URL: Homepage, https://github.com/xen/transforms
Keywords: html,sgml,transforms
Classifier: License :: OSI Approved :: MIT License
Classifier: Programming Language :: Python
Classifier: Programming Language :: Python :: 3
Requires-Python: >=3.7
License-File: LICENSE
